{
  "user1": {
    "id": 1,
    "name": "Munonye",
    "password": "password1",
    "email": "kany@gmail.com"
  },
  "user2": {
    "id": 2,
    "name": "Imolode",
    "password": "password2",
    "email": "saffron@gmail.com"
  },
  "user3": {
    "id": 3,
    "name": "Munonye",
    "password": "password3",
    "email": "othniel@gmail.com"
  },
  "user4": {
    "id": 4,
    "name": "Yuba",
    "password": "password4",
    "email": "oleander@gmail.com"
  },
  "user5": {
    "id": 5,
    "name": "Alex2",
    "password": "password6",
    "email": "alex2@example.com"
  }
}